{
  "type": "excalidraw",
  "version": 2,
  "source": "https://excalidraw.smallweb.localhost",
  "elements": [
    {
      "id": "IZmCQDuSp2l4JCjVzfdTj",
      "type": "rectangle",
      "x": -7199.658689368819,
      "y": -3593.910564502749,
      "width": 876.1749741630092,
      "height": 483.40550335113085,
      "angle": 0,
      "strokeColor": "#1e1e1e",
      "backgroundColor": "transparent",
      "fillStyle": "solid",
      "strokeWidth": 2,
      "strokeStyle": "solid",
      "roughness": 1,
      "opacity": 100,
      "groupIds": [],
      "frameId": null,
      "roundness": {
        "type": 3
      },
      "seed": 852563197,
      "version": 93,
      "versionNonce": 254975869,
      "isDeleted": false,
      "boundElements": null,
      "updated": 1741019046638,
      "link": null,
      "locked": false
    },
    {
      "id": "RSmkPXeJEgdLcgkAq1FSC",
      "type": "rectangle",
      "x": -7074.90501210801,
      "y": -3521.503045015548,
      "width": 204.08603223652244,
      "height": 111.7504491202044,
      "angle": 0,
      "strokeColor": "#1e1e1e",
      "backgroundColor": "transparent",
      "fillStyle": "solid",
      "strokeWidth": 2,
      "strokeStyle": "solid",
      "roughness": 1,
      "opacity": 100,
      "groupIds": [],
      "frameId": null,
      "roundness": {
        "type": 3
      },
      "seed": 1746414333,
      "version": 50,
      "versionNonce": 1695666003,
      "isDeleted": false,
      "boundElements": null,
      "updated": 1741019048906,
      "link": null,
      "locked": false
    },
    {
      "id": "LC8rhFJumxPuo3LYCvYiq",
      "type": "rectangle",
      "x": -6635.474546825413,
      "y": -3522.776041722291,
      "width": 204.08603223652244,
      "height": 111.7504491202044,
      "angle": 0,
      "strokeColor": "#1e1e1e",
      "backgroundColor": "transparent",
      "fillStyle": "solid",
      "strokeWidth": 2,
      "strokeStyle": "solid",
      "roughness": 1,
      "opacity": 100,
      "groupIds": [],
      "frameId": null,
      "roundness": {
        "type": 3
      },
      "seed": 1607764499,
      "version": 95,
      "versionNonce": 1300784659,
      "isDeleted": false,
      "boundElements": null,
      "updated": 1741019049480,
      "link": null,
      "locked": false
    },
    {
      "id": "lCU7VQdKxCPJptGsh8GNz",
      "type": "rectangle",
      "x": -7036.648461863484,
      "y": -3300.9013801124865,
      "width": 495.8022252073715,
      "height": 98.62725270357168,
      "angle": 0,
      "strokeColor": "#1e1e1e",
      "backgroundColor": "transparent",
      "fillStyle": "solid",
      "strokeWidth": 2,
      "strokeStyle": "solid",
      "roughness": 1,
      "opacity": 100,
      "groupIds": [],
      "frameId": null,
      "roundness": {
        "type": 3
      },
      "seed": 2041394525,
      "version": 79,
      "versionNonce": 1166947997,
      "isDeleted": false,
      "boundElements": null,
      "updated": 1741019051813,
      "link": null,
      "locked": false
    },
    {
      "id": "QbE1_g2RXpu39ePm-H-8g",
      "type": "rectangle",
      "x": -6835.788243271273,
      "y": -3301.061337813857,
      "width": 43.74843132492515,
      "height": 72.8673978786419,
      "angle": 0,
      "strokeColor": "#1e1e1e",
      "backgroundColor": "transparent",
      "fillStyle": "solid",
      "strokeWidth": 2,
      "strokeStyle": "solid",
      "roughness": 1,
      "opacity": 100,
      "groupIds": [],
      "frameId": null,
      "roundness": {
        "type": 3
      },
      "seed": 652014429,
      "version": 193,
      "versionNonce": 2054548093,
      "isDeleted": false,
      "boundElements": null,
      "updated": 1741019064509,
      "link": null,
      "locked": false
    },
    {
      "id": "0-bgJabS06A2k3OgpZu4k",
      "type": "rectangle",
      "x": -6792.339732636418,
      "y": -3300.548140188626,
      "width": 37.44343192922406,
      "height": 32.11817345442023,
      "angle": 0,
      "strokeColor": "#1e1e1e",
      "backgroundColor": "transparent",
      "fillStyle": "solid",
      "strokeWidth": 2,
      "strokeStyle": "solid",
      "roughness": 1,
      "opacity": 100,
      "groupIds": [],
      "frameId": null,
      "roundness": {
        "type": 3
      },
      "seed": 247529341,
      "version": 230,
      "versionNonce": 1979643731,
      "isDeleted": false,
      "boundElements": null,
      "updated": 1741019066488,
      "link": null,
      "locked": false
    }
  ],
  "appState": {
    "gridSize": null,
    "viewBackgroundColor": "#ffffff"
  },
  "files": {}
}